flask_maker/__init__.py
flask_maker/cli.py
flask_maker/contents.py
flask_maker/context.py
flask_maker/helpers.py
flask_maker-3.0.0.dist-info/LICENSE
flask_maker-3.0.0.dist-info/METADATA
flask_maker-3.0.0.dist-info/WHEEL
flask_maker-3.0.0.dist-info/entry_points.txt
flask_maker-3.0.0.dist-info/top_level.txt
flask_maker-3.0.0.dist-info/RECORD
